setup.py
src/Hatak_Flashmsg.egg-info/PKG-INFO
src/Hatak_Flashmsg.egg-info/SOURCES.txt
src/Hatak_Flashmsg.egg-info/dependency_links.txt
src/Hatak_Flashmsg.egg-info/namespace_packages.txt
src/Hatak_Flashmsg.egg-info/not-zip-safe
src/Hatak_Flashmsg.egg-info/requires.txt
src/Hatak_Flashmsg.egg-info/top_level.txt
src/haplugin/__init__.py
src/haplugin/flashmsg/__init__.py
src/haplugin/flashmsg/helpers.py
src/haplugin/flashmsg/models.py
src/haplugin/flashmsg/plugin.py
src/haplugin/flashmsg/templates/main.jinja2
src/haplugin/flashmsg/tests/__init__.py
src/haplugin/flashmsg/tests/test_helpers.py
src/haplugin/flashmsg/tests/test_models.py
src/haplugin/flashmsg/tests/test_plugin.py