Metadata-Version: 1.0
Name: Hatak_Flashmsg
Version: 0.1.2
Summary: Flash Messages plugin for Hatak.
Home-page: UNKNOWN
Author: UNKNOWN
Author-email: UNKNOWN
License: Apache License 2.0
Platform: UNKNOWN
